[
    {
        "id": "1",
        "nombre": "ASUS ZenBook Flip",
        "marca": "ASUS",
        "categoria": "Computacion",
        "subcategoria": "Computadoras",
        "subcategoria2": "Notebooks",
        "estado": "Nueva",
        "peso": "2.25 kg",
        "modelo": "UX363EA-HP376T",
        "procesador": " Intel Core i5-1135G7 Processor 2.4 GHz (8M Cache, up to 4.2 GHz, 4 cores)",
        "memoria": "8GB LPDDR4X on board",
        "ranuras memoria": "N/A",
        "disco duro": "512GB M.2 NVMe PCIe® 3.0 SSD",
        "sistema operativo": "Windows 10 Home",
        "graficos": "Intel Iris Xe Graphics",
        "puertos": "1x HDMI 1.4--1x USB 3.2 Gen 1 Type-A",
        "sonido": "SonicMaster",
        "color": "Grey (gris)",
        "garantia": "1 AÑO",
        "precio": 1280,
        "disponible": 1,
        "imagen": "imagenes/ASUS_ZenBook_Flip_I1.jpg"
    },
    {
        "id": "2",
        "nombre": "ASUS ROG Zephyrus GA401QC-HZ026T",
        "marca": "ASUS",
        "categoria": "Computacion",
        "subcategoria": "Computadoras",
        "subcategoria2": "Notebooks",
        "estado": "Nueva",
        "peso": "4.89 kg",
        "modelo": "GA401QC-HZ026T",
        "procesador": "AMD Ryzen 7 5800HS Processor 3.0 GHz (16M Cache, up to 4.3 GHz)",
        "memoria": "8GB DDR4 on board",
        "ranuras memoria": "N/A",
        "disco duro": "512GB M.2 NVMe PCIe 3.0 SSD",
        "sistema operativo": "Windows 10 Home",
        "graficos": "NVIDIA GeForce RTX™ 3050 Laptop GPU, 4GB GDDR6",
        "puertos": "1x USB 3.2 Gen 2 Type-C, 1x USB 3.2 Gen 2 Type-C support DisplayPort™ / power delivery / G-SYNC, 2x USB 3.2 Gen 1 Type-A--1x 3.5mm Combo Audio Jack",
        "sonido": "Audio by Dolby Atmos",
        "color": "Grey (gris), Eclipse Gray AniMe Matrix version",
        "garantia": "1 AÑO",
        "precio": 1880,
        "disponible": 1,
        "imagen": "imagenes/ASUS_ROG_Zephyrus_I1.jpg"
    },
    {
        "id": "3",
        "nombre": "ASUS ROG Zephyrus COMASU05T6M0043",
        "marca": "ASUS",
        "categoria": "Computacion",
        "subcategoria": "Computadoras",
        "subcategoria2": "Notebooks",
        "estado": "Nueva",
        "peso": "4.87 kg",
        "modelo": "GA401IV-HA129T",
        "procesador": "AMD Ryzen™ 9 4900HS Processor 3.0 GHz (8M Cache, up to 4.3 GHz)",
        "memoria": "8GB DDR4 on board + 8GB DDR4-3200 SO-DIMM",
        "ranuras memoria": "1x SO-DIMM slot",
        "disco duro": "M.2 1TB G3x2 PCIe SSD",
        "sistema operativo": "Windows 10 Home",
        "graficos": "NVIDIA® GeForce RTX™ 2060 with Max-Q Design, 6GB GDDR6",
        "puertos": "1x USB 3.2 Gen 2 Type-C, 2x USB 3.2 Gen 1 Type-A, 1x Type C USB 3.2 Gen 2 with Power Delivery, Display Port and G-Sync--1x 3.5mm Combo Audio Jack",
        "sonido": "Smart Amp Technology, Dolby Atmos Software",
        "color": "Grey (gris) w- LED",
        "garantia": "1 AÑO",
        "precio": 2278,
        "disponible": 1,
        "imagen": "imagenes/ASUS_ROG_Zephyrus_I2.jpg"
    },
    {
        "id": "4",
        "nombre": "DELL NoteBook LATITUDE 3420",
        "marca": "DELL",
        "categoria": "Computacion",
        "subcategoria": "Computadoras",
        "subcategoria2": "Notebooks",
        "estado": "Nueva",
        "peso": "2.45 kg",
        "modelo": "LATITUDE 3420",
        "procesador": "11th Generation Intel® Core™ i3-1115G4 (2 Core, 6M cache, base 3.0GHz, up to 4.10 GHz)",
        "memoria": "4GB, 1x8GB, DDR4 Non-ECC",
        "ranuras memoria": "2 Slot",
        "disco duro": "1TB 2.5 5400RPM 7mm Toshiba",
        "sistema operativo": "UBUNTU LINUX",
        "graficos": "Discount i3 Special Use Only, Intel i3-1115G4, Integrated Intel UHD Graphics",
        "puertos": "USB 3.2 (3x), USB 2.0 (1x), HDMI , RJ-45",
        "sonido": "Si",
        "pantalla": "14 HD (1366 x 768) Anti-Glare Non-Touch, Camera & Microphone, WLAN Capable",
        "color": "Negro",
        "garantia": "1 AÑO",
        "precio": 690,
        "disponible": 1,
        "imagen": "imagenes/DELL_LATITUDE_3420_I1.jpg"
    },
    {
        "id": "5",
        "nombre": "DELL NoteBook LATITUDE 3420",
        "marca": "DELL",
        "categoria": "Computacion",
        "subcategoria": "Computadoras",
        "subcategoria2": "Notebooks",
        "estado": "Nueva",
        "peso": "2.4 kg",
        "modelo": "LATITUDE 3420",
        "procesador": "11th Generation Intel® Core™ i5-1135G7 (4 Core, 8M cache, base 2.4GHz, up to 4.2GHz)",
        "memoria": "8 GB, 1X8 GB 3200MHz DDR4 Non-ECC",
        "ranuras memoria": "2 Slot",
        "disco duro": "M.2 2230 256GB PCIe C35 SSD",
        "sistema operativo": "Windows 10 Pro English, French, Spanish",
        "graficos": "Intel Integrated Graphics",
        "puertos": "1 USB 3.2 Gen 1 port 1 USB 3.2 Gen 1 port with PowerShare 1 USB 2.0 port - HDMI - RJ45",
        "sonido": "Si",
        "pantalla": "14 HD (1366 x 768) Anti-Glare Non-Touch, Camera & Microphone, WLAN Capable",
        "color": "Negro",
        "garantia": "1 AÑO",
        "precio": 1120,
        "disponible": 1,
        "imagen": "imagenes/DELL_LATITUDE_3420_I2.jpg"
    },
    {
        "id": "6",
        "nombre": "DELL Comp VOSTRO 3681",
        "marca": "DELL",
        "categoria": "Computacion",
        "subcategoria": "Computadoras",
        "subcategoria2": "PC-Desktop",
        "estado": "Nueva",
        "peso": "6.23 kg",
        "modelo": "Vostro 3681",
        "procesador": "10th Gen Intel® Core™ i5-10400 processor(6-Core, 12M Cache, 2.9GHz to 4.3GHz)",
        "memoria": "8GB, 1x8GB, DDR4, 2666MHz",
        "ranuras memoria": "2 Slot",
        "disco duro": "3.5inch 1TB 7200 rpm SATA Hard Drive",
        "sistema operativo": "Windows 10 Pro English, French, Spanish",
        "graficos": "Intel® UHD Graphics 630 with shared graphics memory",
        "puertos": "(4x) USB 3.2 Gen, (2x) USB 2.0 Type-A, (2x) USB 2.0 Type-A, HDMI, RJ-45, VGA",
        "sonido": "Si",
        "pantalla": "N/A",
        "color": "Negro",
        "garantia": "1 AÑO",
        "precio": 907,
        "disponible": 1,
        "imagen": "imagenes/DELL_Comp_VOSTRO_3681.jpg"
    },
    {
        "id": "7",
        "nombre": "DELL NoteBook LATITUDE 3410",
        "marca": "DELL",
        "categoria": "Computacion",
        "subcategoria": "Computadoras",
        "subcategoria2": "Notebooks",
        "estado": "Nueva",
        "peso": "2.38 kg",
        "modelo": "LATITUDE 3410",
        "procesador": "10th Generation Intel® Core™ i5-10210U (4 Core, 6M cache, base 1.6GHz, up to 4.2GHz)",
        "memoria": "8GB, 1x8GB, DDR4 Non-ECC",
        "ranuras memoria": "2 Slot",
        "disco duro": "M.2 2230 256GB PCIe C35 SSD",
        "sistema operativo": "Windows 10 Pro English, French, Spanish",
        "graficos": "Intel Integrated Graphics",
        "puertos": "1 USB 3.2 Gen 1 port 1 USB 3.2 Gen 1 port with PowerShare 1 USB 2.0 port - HDMI - RJ45",
        "sonido": "Si",
        "pantalla": "14 HD (1366 x 768) Anti-Glare Non-Touch, Camera & Microphone, WLAN Capable",
        "color": "Space Gray",
        "garantia": "1 AÑO",
        "precio": 940,
        "disponible": 1,
        "imagen": "imagenes/DELL_LATITUDE_3410.jpg"
    },
    {
        "id": "8",
        "nombre": "DELL NoteBook VOSTRO 3400",
        "marca": "DELL",
        "categoria": "Computacion",
        "subcategoria": "Computadoras",
        "subcategoria2": "Notebooks",
        "estado": "Nueva",
        "peso": "2.46 kg",
        "modelo": "Vostro 3400",
        "procesador": "11th Generation Intel Core i5-1135G7 Processor (8MB Cache, up to 4.2 GHz)",
        "memoria": "8GB, 8Gx1, DDR4, 3200MHz_2666MHz Ach",
        "ranuras memoria": "2 Slot",
        "disco duro": "1TB 5.4K HDD 2.5",
        "sistema operativo": " Windows 10 Pro 64bit English, French, Spanish",
        "graficos": "Intel Iris Xe Graphics with shared graphics memory",
        "puertos": "USB 3.2 Gen 1 (x2), USB2.0 (x1), USB 3.2 Gen 1, HDMI (1x)",
        "sonido": "Si",
        "pantalla": "14.0-inch HD (1366 x 768) Anti-glare LED Backlight Non-touch Narrow Border Display",
        "color": "Negro",
        "garantia": "1 AÑO",
        "precio": 962,
        "disponible": 1,
        "imagen": "imagenes/DELL_VOSTRO_3400.jpg"
    },
    {
        "id": "9",
        "nombre": "DELL NoteBook INSPIRON  2 en 1",
        "marca": "DELL",
        "categoria": "Computacion",
        "subcategoria": "Computadoras",
        "subcategoria2": "Notebooks",
        "estado": "Nueva",
        "peso": "2.35 kg",
        "modelo": "Inspiron 5410",
        "procesador": "11th Generation Intel® Core™ i5-1135G7 Processor (8MB Cache, up to 4.2 GHz)",
        "memoria": "8GB",
        "ranuras memoria": "2 Slot",
        "disco duro": "256GB CL35 M.2 SSD",
        "sistema operativo": "Windows 10 Home Español",
        "graficos": "Gráficos Intel® Iris® Xe con memoria gráfica compartida",
        "puertos": "1 x USB 4.0 Type-C (full feature), 2 x USB 3.1 Gen1 Type-A, HDMI",
        "sonido": "Si",
        "pantalla": "Pantalla WVA de borde estrecho FHD (1920 x 1080) Truelife Touch de 14,0 pulgadas",
        "color": "Silver",
        "garantia": "1 AÑO",
        "precio": 1075,
        "disponible": 1,
        "imagen": "imagenes/DELL_INSPIRON_2en1.jpg"
    },
    {
        "id": "10",
        "nombre": "DELL NoteBook VOSTRO 5410",
        "marca": "DELL",
        "categoria": "Computacion",
        "subcategoria": "Computadoras",
        "subcategoria2": "Notebooks",
        "estado": "Nueva",
        "peso": "2.29 kg",
        "modelo": "Vostro 5410",
        "procesador": "11th Generation Intel® Core™ i5-11300H Processor (8MB Cache, up to 4.4GHz)",
        "memoria": "8GB DDR4 3200MHz",
        "ranuras memoria": "2 Slot",
        "disco duro": "256GB CL35 M.2 SSD",
        "sistema operativo": "Windows 10 Pro English, French, Spanish",
        "graficos": "Intel® Iris® Xe Graphics with shared graphics memory",
        "puertos": "1x USB 4.0, 2x USB 3.2 Type-A, HDMI 1.4",
        "sonido": "Si",
        "pantalla": "14.0-inch FHD (1920 x 1080) Anti-glare LED Backlight Non-Touch Narrow Border WVA Display",
        "color": "Gray (gris)",
        "garantia": "1 AÑO",
        "precio": 1115,
        "disponible": 1,
        "imagen": "imagenes/DELL_VOSTRO_5410.jpg"
    } 
]